{"SURVIVAL":{"enderChestContents":{},"offHandItem":{"==":"org.bukkit.inventory.ItemStack","v":3955,"type":"AIR","amount":0},"armorContents":{"0":{"==":"org.bukkit.inventory.ItemStack","v":3955,"type":"LEATHER_BOOTS","meta":{"==":"ItemMeta","meta-type":"COLORABLE_ARMOR","Damage":10}},"1":{"==":"org.bukkit.inventory.ItemStack","v":3955,"type":"LEATHER_LEGGINGS","meta":{"==":"ItemMeta","meta-type":"COLORABLE_ARMOR","Damage":10}},"2":{"==":"org.bukkit.inventory.ItemStack","v":3955,"type":"LEATHER_CHESTPLATE","meta":{"==":"ItemMeta","meta-type":"COLORABLE_ARMOR","Damage":10}},"3":{"==":"org.bukkit.inventory.ItemStack","v":3955,"type":"LEATHER_HELMET","meta":{"==":"ItemMeta","meta-type":"COLORABLE_ARMOR","Damage":10}}},"inventoryContents":{"36":{"==":"org.bukkit.inventory.ItemStack","v":3955,"type":"LEATHER_BOOTS","meta":{"==":"ItemMeta","meta-type":"COLORABLE_ARMOR","Damage":10}},"37":{"==":"org.bukkit.inventory.ItemStack","v":3955,"type":"LEATHER_LEGGINGS","meta":{"==":"ItemMeta","meta-type":"COLORABLE_ARMOR","Damage":10}},"38":{"==":"org.bukkit.inventory.ItemStack","v":3955,"type":"LEATHER_CHESTPLATE","meta":{"==":"ItemMeta","meta-type":"COLORABLE_ARMOR","Damage":10}},"39":{"==":"org.bukkit.inventory.ItemStack","v":3955,"type":"LEATHER_HELMET","meta":{"==":"ItemMeta","meta-type":"COLORABLE_ARMOR","Damage":10}}},"potions":[],"stats":{"ex":"3.7833142","ma":"300","fl":"17","el":"1","xp":"0.88888896","hp":"15.859997749328613","txp":"15","ft":"-20","sa":"0.0","fd":"0.0","ra":"300"}}}